Workbook
Name Div_mensal: Investimento_Por_FII!$D$23
Name Investir_mes: Investimento_Por_FII!$D$19
Name Patrimonio_acumulado: Investimento_Por_FII!$D$22
Name Qtd_10_anos: Investimento_Por_FII!$D$28
Name Qtd_15_anos: Investimento_Por_FII!$D$29
Name Qtd_2_anos: Investimento_Por_FII!$D$26
Name Qtd_20_anos: Investimento_Por_FII!$D$30
Name Qtd_25_anos: Investimento_Por_FII!$D$31
Name Qtd_30_anos: Investimento_Por_FII!$D$32
Name Qtd_5_anos: Investimento_Por_FII!$D$27
Name Quantos_anos: Investimento_Por_FII!$D$20
Name Rend_carteira: Investimento_Por_FII!$D$15
Name Rendimento_mensal: Investimento_Por_FII!$D$21
Name Salario: Investimento_Por_FII!$D$14
Name sugestao_investimento: Investimento_Por_FII!$D$16

Sheet Investimento_Por_FII
B13: BASE INVESTIMENTOS
B14: Salário mensal | D14: 5200
B15: Rendimento da carteira | D15: 0.01
B16: Sugestão de investimento | D16: 0.15
B18: INVESTIMENTO MENSAL
B19: Quanto invertir por mês? | D19: =D16 * (1 + D14) -> 780.15
B20: Por quantos anos? | D20: 30
B21: Taxa de rendimento mensal? | D21: =$D$15 -> 0.01
B22: Patrimônio acumulado? | D22: =FV(Rendimento_mensal,Quantos_anos*12,Investir_mes*-1) -> 2726596.3
B23: Dividendos mensais? | D23: =Patrimonio_acumulado*Rend_carteira -> 27265.963
B25: CENÁRIOS | D25: Dividendo
A26: 2 | B26: Quanto em 2 anos? | C26: =FV(Rendimento_mensal,$A26*12,Investir_mes*-1) -> 21043.349 | D26: =$C26*Rendimento_mensal -> 210.43349
A27: 5 | B27: Quanto em 5 anos? | C27: =FV(Rendimento_mensal,$A27*12,Investir_mes*-1) -> 63714.593 | D27: =$C27*Rendimento_mensal -> 637.14593
A28: 10 | B28: Quanto em 10 anos? | C28: =FV(Rendimento_mensal,$A28*12,Investir_mes*-1) -> 179464.68 | D28: =$C28*Rendimento_mensal -> 1794.6468
A29: 15 | B29: Quanto em 15 anos? | C29: =FV(Rendimento_mensal,$A29*12,Investir_mes*-1) -> 389747.49 | D29: =$C29*Rendimento_mensal -> 3897.4749
A30: 20 | B30: Quanto em 20 anos? | C30: =FV(Rendimento_mensal,$A30*12,Investir_mes*-1) -> 771767.57 | D30: =$C30*Rendimento_mensal -> 7717.6757
A31: 25 | B31: Quanto em 25 anos? | C31: =FV(Rendimento_mensal,$A31*12,Investir_mes*-1) -> 1465782.2 | D31: =$C31*Rendimento_mensal -> 14657.822
A32: 30 | B32: Quanto em 30 anos? | C32: =FV(Rendimento_mensal,$A32*12,Investir_mes*-1) -> 2726596.3 | D32: =$C32*Rendimento_mensal -> 27265.963
B34: PERFIL | C34: Conservador
B35: VALOR INVETIDO MENSALMENTE | C35: =Investir_mes -> 780.15
B37: TIPO DE FII | C37: Percentual Sugerido | D37: Valores
B38: PAPEL | C38: =VLOOKUP($C$34&"-"&B38,Perfil_Investidor!$B:$E,4,FALSE) -> 0.6 | D38: =$C$35 * C38 -> 468.09
B39: TIJOLO | C39: =VLOOKUP($C$34&"-"&B39,Perfil_Investidor!$B:$E,4,FALSE) -> 0.2 | D39: =$C$35 * C39 -> 156.03
B40: HÍBRIDOS | C40: =VLOOKUP($C$34&"-"&B40,Perfil_Investidor!$B:$E,4,FALSE) -> 0.1 | D40: =$C$35 * C40 -> 78.015
B41: FOFs | C41: =VLOOKUP($C$34&"-"&B41,Perfil_Investidor!$B:$E,4,FALSE) -> 0.05 | D41: =$C$35 * C41 -> 39.0075
B42: DESENVOLVIMENTO | C42: =VLOOKUP($C$34&"-"&B42,Perfil_Investidor!$B:$E,4,FALSE) -> 0.03 | D42: =$C$35 * C42 -> 23.4045
B43: HOTELARIAS | C43: =VLOOKUP($C$34&"-"&B43,Perfil_Investidor!$B:$E,4,FALSE) -> 0.02 | D43: =$C$35 * C43 -> 15.603
B44: TOTAL | D44: =SUM(D38:D43) -> 780.15

Sheet Perfil_Investidor
B2: CHAVE | C2: Perfil | D2: Tipo FII | E2: Percentual | F2: Soma de Percentual | G2: Rótulos de Coluna
B3: =C3&"-"&D3 -> Conservador-Papel | C3: Conservador | D3: Papel | E3: 0.6 | F3: Rótulos de Linha | G3: Desenvolvimento | H3: FOFs | I3: Híbridos | J3: Hotelarias | K3: Papel | L3: Tijolo | M3: Total Geral
B4: =C4&"-"&D4 -> Conservador-Tijolo | C4: Conservador | D4: Tijolo | E4: 0.2 | F4: Agressivo | G4: 15 | H4: 10 | I4: 25 | J4: 5 | K4: 15 | L4: 30 | M4: 100
B5: =C5&"-"&D5 -> Conservador-Híbridos | C5: Conservador | D5: Híbridos | E5: 0.1 | F5: Conservador | G5: 3 | H5: 5 | I5: 10 | J5: 2 | K5: 60 | L5: 20 | M5: 100
B6: =C6&"-"&D6 -> Conservador-FOFs | C6: Conservador | D6: FOFs | E6: 0.05 | F6: Moderado | G6: 3 | H6: 10 | I6: 20 | J6: 2 | K6: 35 | L6: 30 | M6: 100
B7: =C7&"-"&D7 -> Conservador-Desenvolvimento | C7: Conservador | D7: Desenvolvimento | E7: 0.03
B8: =C8&"-"&D8 -> Conservador-Hotelarias | C8: Conservador | D8: Hotelarias | E8: 0.02
B9: =C9&"-"&D9 -> Moderado-Papel | C9: Moderado | D9: Papel | E9: 0.35
B10: =C10&"-"&D10 -> Moderado-Tijolo | C10: Moderado | D10: Tijolo | E10: 0.3
B11: =C11&"-"&D11 -> Moderado-Híbridos | C11: Moderado | D11: Híbridos | E11: 0.2
B12: =C12&"-"&D12 -> Moderado-FOFs | C12: Moderado | D12: FOFs | E12: 0.1
B13: =C13&"-"&D13 -> Moderado-Desenvolvimento | C13: Moderado | D13: Desenvolvimento | E13: 0.03
B14: =C14&"-"&D14 -> Moderado-Hotelarias | C14: Moderado | D14: Hotelarias | E14: 0.02
B15: =C15&"-"&D15 -> Agressivo-Papel | C15: Agressivo | D15: Papel | E15: 0.15
B16: =C16&"-"&D16 -> Agressivo-Tijolo | C16: Agressivo | D16: Tijolo | E16: 0.3
B17: =C17&"-"&D17 -> Agressivo-Híbridos | C17: Agressivo | D17: Híbridos | E17: 0.25
B18: =C18&"-"&D18 -> Agressivo-FOFs | C18: Agressivo | D18: FOFs | E18: 0.1
... B20: =C20&"-"&D20 -> Agressivo-Hotelarias | C20: Agressivo | D20: Hotelarias | E20: 0.05
B22: Conservador-Papel | C22: =VLOOKUP(B22,$B2:$E20,4,FALSE) -> 0.6
B24: Tipo FII | C24: Agressivo | D24: Conservador | E24: Moderado
B25: Desenvolvimento | C25: 0.15 | D25: 0.03 | E25: 0.03
B26: FOFs | C26: 0.1 | D26: 0.05 | E26: 0.1
B27: Hotelarias | C27: 0.05 | D27: 0.02 | E27: 0.02
B28: Híbridos | C28: 0.25 | D28: 0.1 | E28: 0.2
B29: Papel | C29: 0.15 | D29: 0.6 | E29: 0.25
B30: Tijolo | C30: 0.03 | D30: 0.2 | E30: 0.3
